raidpy/__init__.py
raidpy/absorption.py
raidpy/collision.py
raidpy/constants.py
raidpy/doppler.py
raidpy/functions.py
raidpy/iono.py
raidpy/phase.py
raidpy/plots.py
raidpy/utils.py
raidpy/ionosphere/__init__.py
raidpy/ionosphere/igrf13.py
raidpy/ionosphere/iri.py
raidpy/ionosphere/msise.py
raidpy-0.1.7.dist-info/licenses/LICENSE
raidpy-0.1.7.dist-info/METADATA
raidpy-0.1.7.dist-info/WHEEL
raidpy-0.1.7.dist-info/top_level.txt
raidpy-0.1.7.dist-info/RECORD
